LICENSE.txt
MANIFEST.in
README.md
setup.cfg
setup.py
containers_dock/__init__.py
containers_dock/__main__.py
containers_dock/app.py
containers_dock/components.py
containers_dock/config.ini
containers_dock/controllers.py
containers_dock/mappers.py
containers_dock/models.py
containers_dock/threads.py
containers_dock/utils.py
containers_dock.egg-info/PKG-INFO
containers_dock.egg-info/SOURCES.txt
containers_dock.egg-info/dependency_links.txt
containers_dock.egg-info/entry_points.txt
containers_dock.egg-info/requires.txt
containers_dock.egg-info/top_level.txt