Metadata-Version: 1.1
Name: containers-dock
Version: 0.3.4
Summary: Application used to control docker containers.
Home-page: UNKNOWN
Author: Todor Todorov
Author-email: todstoychev@gmail.com
License: UNKNOWN
Keywords: docker containers control
Platform: UNKNOWN
Classifier: Intended Audience :: Developers
Classifier: Topic :: Software Development :: Build Tools
Classifier: License :: OSI Approved :: MIT License
Classifier: Programming Language :: Python :: 3.5
Classifier: Programming Language :: Python :: 3.6
Classifier: Programming Language :: Python :: 3.7
